hwmux_client/__init__.py
hwmux_client/api_client.py
hwmux_client/api_client_async.py
hwmux_client/configuration.py
hwmux_client/exceptions.py
hwmux_client/hwmux_api.py
hwmux_client/model_utils.py
hwmux_client/rest.py
hwmux_client/rest_async.py
hwmux_client/api/__init__.py
hwmux_client/api/callback_api.py
hwmux_client/api/devices_api.py
hwmux_client/api/django_login_api.py
hwmux_client/api/external_signin_api.py
hwmux_client/api/groups_api.py
hwmux_client/api/labels_api.py
hwmux_client/api/logs_api.py
hwmux_client/api/outbox_api.py
hwmux_client/api/part_families_api.py
hwmux_client/api/parts_api.py
hwmux_client/api/permissions_api.py
hwmux_client/api/reservations_api.py
hwmux_client/api/rooms_api.py
hwmux_client/api/schema_api.py
hwmux_client/api/signin_api.py
hwmux_client/api/signout_api.py
hwmux_client/api/sites_api.py
hwmux_client/api/token_auth_api.py
hwmux_client/api/user_api.py
hwmux_client/apis/__init__.py
hwmux_client/model/__init__.py
hwmux_client/model/auth_token.py
hwmux_client/model/blank_enum.py
hwmux_client/model/device_group.py
hwmux_client/model/device_group_serializer_with_device_pk.py
hwmux_client/model/device_serializer_public.py
hwmux_client/model/event_enum.py
hwmux_client/model/group_location.py
hwmux_client/model/label.py
hwmux_client/model/label_serializer_with_permissions.py
hwmux_client/model/light_device.py
hwmux_client/model/location.py
hwmux_client/model/location_serializer_write_only.py
hwmux_client/model/log.py
hwmux_client/model/log_resource_type.py
hwmux_client/model/log_status_enum.py
hwmux_client/model/logged_in_user.py
hwmux_client/model/nested_device_group.py
hwmux_client/model/null_enum.py
hwmux_client/model/object_permissions.py
hwmux_client/model/outbox.py
hwmux_client/model/outbox_reservation_status.py
hwmux_client/model/outbox_status_enum.py
hwmux_client/model/paginated_device_group_list.py
hwmux_client/model/paginated_device_serializer_public_list.py
hwmux_client/model/paginated_label_list.py
hwmux_client_python-2.46.2.dist-info/METADATA
hwmux_client_python-2.46.2.dist-info/WHEEL
hwmux_client_python-2.46.2.dist-info/top_level.txt
hwmux_client_python-2.46.2.dist-info/RECORD
