Metadata-Version: 2.1
Name: hwmux-client-python
Version: 2.46.2
Summary: HW Mux Reservation System
Home-page: 
Author: OpenAPI Generator community
Author-email: team@openapitools.org
Keywords: OpenAPI,OpenAPI-Generator,HW Mux Reservation System
Requires-Python: >=3.6
Requires-Dist: urllib3>=1.25.3
Requires-Dist: python-dateutil
Requires-Dist: httpx~=0.27.0
